vowelextractor_pip/__init__.py
vowelextractor_pip/version.py
vowelextractor_pip/vowelextractor_pip.py
vowelextractor_pip-0.0.1.dist-info/METADATA
vowelextractor_pip-0.0.1.dist-info/WHEEL
vowelextractor_pip-0.0.1.dist-info/licenses/LICENSE
vowelextractor_pip-0.0.1.dist-info/RECORD
